polarion_docstrings/__init__.py
polarion_docstrings/checker.py
polarion_docstrings/flake8_plugin.py
polarion_docstrings/parser.py
polarion_docstrings/utils.py
polarion_docstrings-0.26.0.dist-info/METADATA
polarion_docstrings-0.26.0.dist-info/WHEEL
polarion_docstrings-0.26.0.dist-info/entry_points.txt
polarion_docstrings-0.26.0.dist-info/top_level.txt
polarion_docstrings-0.26.0.dist-info/RECORD
